nightscout/__init__.py
nightscout/api.py
nightscout/models.py
nightscout/schedule_test.py
python_nightscout-1.0.0.dist-info/METADATA
python_nightscout-1.0.0.dist-info/WHEEL
python_nightscout-1.0.0.dist-info/top_level.txt
python_nightscout-1.0.0.dist-info/RECORD
