Metadata-Version: 2.1
Name: python-nightscout
Version: 1.0.0
Summary: A library that provides a Python interface to Nightscout
Home-page: https://github.com/ps2/python-nightscout
Author: Pete Schwamb
Author-email: pete@schwamb.net
License: MIT
Keywords: nightscout api client development
Classifier: Development Status :: 3 - Alpha
Classifier: Intended Audience :: Developers
Classifier: License :: OSI Approved :: MIT License
Classifier: Programming Language :: Python :: 2.7
Requires-Dist: requests
Requires-Dist: python-dateutil
Requires-Dist: pytz
Provides-Extra: dev
Requires-Dist: check-manifest ; extra == 'dev'
Provides-Extra: test
Requires-Dist: coverage ; extra == 'test'
Requires-Dist: httmock ; extra == 'test'
